DataStructuresSerialized.py
README.rst
setup.py
DataStructuresSerialized.egg-info/PKG-INFO
DataStructuresSerialized.egg-info/SOURCES.txt
DataStructuresSerialized.egg-info/dependency_links.txt
DataStructuresSerialized.egg-info/top_level.txt
tests/__init__.py
tests/tests.py