Metadata-Version: 1.1
Name: DataStructuresSerialized
Version: 0.0.3
Summary: python data structures(tuple list OrderedDict) serialized
Home-page: https://github.com/laodifang/DataStructuresSerialized
Author: Ren Peng
Author-email: ithink.ren@gmail.com
License: MIT
Keywords: data structures list serialized deserialization
Platform: UNKNOWN
Classifier: Development Status :: 5 - Production/Stable
Classifier: Intended Audience :: Developers
Classifier: License :: OSI Approved :: MIT License
Classifier: Programming Language :: Python :: 3.4
Classifier: Programming Language :: Python :: 3 :: Only
